sc2xmlreader/__init__.py
sc2xmlreader/const.py
sc2xmlreader/sc2xmlreader.py
sc2xmlreader/sc2xmlreader_validator.py
sc2xmlreader-0.1.2.dist-info/METADATA
sc2xmlreader-0.1.2.dist-info/WHEEL
sc2xmlreader-0.1.2.dist-info/licenses/LICENSE
sc2xmlreader-0.1.2.dist-info/RECORD
