Metadata-Version: 2.1
Name: sc2xmlreader
Version: 0.1.2
Summary: Reads and interprets XML data from solvis remote device
Project-URL: Homepage, https://github.com/Lurchi70/sc2xmlreader_pypi_package
Project-URL: Bug Tracker, https://github.com/Lurchi70/sc2xmlreader_pypi_package/issues
Author-email: lurchi70 <hjleu@web.de>
License-File: LICENSE
Classifier: License :: OSI Approved :: MIT License
Classifier: Operating System :: OS Independent
Classifier: Programming Language :: Python :: 3
Requires-Python: >=3.7
Requires-Dist: defusedxml
Requires-Dist: requests
Requires-Dist: urllib3
